babelfish/__init__.py
babelfish/converters/__init__.py
babelfish/converters/alpha2.py
babelfish/converters/alpha3b.py
babelfish/converters/alpha3t.py
babelfish/converters/countryname.py
babelfish/converters/name.py
babelfish/converters/opensubtitles.py
babelfish/converters/scope.py
babelfish/converters/type.py
babelfish/country.py
babelfish/data/iso-3166-1.txt
babelfish/data/iso-639-3.tab
babelfish/data/iso15924-utf8-20131012.txt
babelfish/data/opensubtitles_languages.txt
babelfish/exceptions.py
babelfish/language.py
babelfish/script.py
babelfish-0.6.0b1.dist-info/LICENSE
babelfish-0.6.0b1.dist-info/WHEEL
babelfish-0.6.0b1.dist-info/METADATA
babelfish-0.6.0b1.dist-info/RECORD
