Metadata-Version: 2.1
Name: babelfish
Version: 0.6.0b1
Summary: A module to work with countries and languages
Home-page: https://github.com/Diaoul/babelfish
License: BSD-3-Clause
Keywords: language,country,locale
Author: Antoine Bertin
Author-email: ant.bertin@gmail.com
Requires-Python: >=3.6,<4.0
Classifier: Development Status :: 5 - Production/Stable
Classifier: Intended Audience :: Developers
Classifier: License :: OSI Approved :: BSD License
Classifier: Operating System :: OS Independent
Classifier: Programming Language :: Python
Classifier: Programming Language :: Python :: 3
Classifier: Programming Language :: Python :: 3 :: Only
Classifier: Programming Language :: Python :: 3.6
Classifier: Programming Language :: Python :: 3.7
Classifier: Programming Language :: Python :: 3.8
Classifier: Programming Language :: Python :: 3.9
Classifier: Topic :: Software Development :: Internationalization
Classifier: Topic :: Software Development :: Libraries :: Python Modules
Project-URL: Repository, https://github.com/Diaoul/babelfish
